[
  {
    "id": 1,
    "name": "yogesh",
    "email": "yogeh@hdwb.asbh"
  },
  {
    "id": 2,
    "name": "fyg",
    "email": "ewrt@hdwb.asbh"
  },
  {
    "id": 3,
    "name": "sfdg",
    "email": "ert@hdwb.asbh"
  },
  {
    "id": 4,
    "name": "tyu",
    "email": "tyds@hdwb.asbh"
  },
  {
    "id": 5,
    "name": "qwewr",
    "email": "qerdvf@hdwb.asbh"
  },
  {
    "id": 6,
    "name": "ret",
    "email": "rerwty@hdwb.asbh"
  },
  {
    "id":7,
    "name":"iuhg",
    "email": "iuytr@hdwb.asbh"
        },
        {
            "id":8,
            "name":"lkj",
            "email": "lkjh@hdwb.asbh"
                },
                {
                    "id":9,
                    "name":"oijhb",
                    "email": "oijh@hdwb.asbh"
                        }
]
